<sync>
    <local>
        <angle>EAST</angle>
        <depth>50868</depth>
        <video>1196</video>
    </local>
    <local>
        <angle>NORTH</angle>
        <depth>50908</depth>
        <video>1246</video>
    </local>
    <local>
        <angle>SOUTH</angle>
        <depth>50884</depth>
        <video>1238</video>
    </local>
    <local>
        <angle>WEST</angle>
        <depth>50899</depth>
        <video>1229</video>
    </local>
    <global>
        <angle>EAST</angle>
        <depth>50868</depth>
    </global>
    <global>
        <angle>NORTH</angle>
        <depth>50908</depth>
    </global>
    <global>
        <angle>SOUTH</angle>
        <depth>50884</depth>
    </global>
    <global>
        <angle>WEST</angle>
        <depth>50899</depth>
    </global>
</sync>
